src/__init__.py
src/main.py
fast_api_kube-0.3.dist-info/LICENSE
fast_api_kube-0.3.dist-info/METADATA
fast_api_kube-0.3.dist-info/WHEEL
fast_api_kube-0.3.dist-info/top_level.txt
fast_api_kube-0.3.dist-info/RECORD
