Metadata-Version: 2.1
Name: fast-api-kube
Version: 0.3
Summary: fast-api-kube
Home-page: https://github.com/maher-naija-pro/fast-api-kube
Author: maher naija
Author-email: maher.naija@gmail.Com
License: MIT
License-File: LICENSE
